par_bgc_argo_pitarch/__init__.py
par_bgc_argo_pitarch/par_from_Ed_380_412_443_490_555_v5.py
par_bgc_argo_pitarch/par_from_Ed_380_412_490_v5.py
par_bgc_argo_pitarch/par_from_Ed_380_443_490_555_v5.py
par_bgc_argo_pitarch/par_from_Ed_380_443_490_560_v5.py
par_bgc_argo_pitarch/par_from_Ed_380_490_555_665_v5.py
par_bgc_argo_pitarch-0.1.0.dist-info/licenses/LICENSE
par_bgc_argo_pitarch-0.1.0.dist-info/METADATA
par_bgc_argo_pitarch-0.1.0.dist-info/WHEEL
par_bgc_argo_pitarch-0.1.0.dist-info/top_level.txt
par_bgc_argo_pitarch-0.1.0.dist-info/RECORD
