Metadata-Version: 2.4
Name: par-bgc-argo-pitarch
Version: 0.1.0
Summary: PAR BGC Argo data processing
Author-email: Your Name <jaime.pitarch@cnr.it>
License: GNU GENERAL PUBLIC LICENSE
Project-URL: Homepage, https://github.com/jaipipor/PAR_BGC_Argo
Project-URL: Repository, https://github.com/jaipipor/PAR_BGC_Argo
Classifier: License :: OSI Approved :: GNU General Public License v3 (GPLv3)
Requires-Python: >=3.8
License-File: LICENSE
Requires-Dist: numpy
Requires-Dist: scipy
Dynamic: license-file
